<?xml version="1.0"?>
<ArrayOfProductGroupMembership xmlns:xsi="http://www.w3.org/2001/XMLSchema-instance" xmlns:xsd="http://www.w3.org/2001/XMLSchema">
  <ProductGroupMembership>
    <ProductId>2</ProductId>
    <ProductGroupId>01</ProductGroupId>
  </ProductGroupMembership>
  <ProductGroupMembership>
    <ProductId>2</ProductId>
    <ProductGroupId>0103</ProductGroupId>
  </ProductGroupMembership>
  <ProductGroupMembership>
    <ProductId>1</ProductId>
    <ProductGroupId>01</ProductGroupId>
  </ProductGroupMembership>
  <ProductGroupMembership>
    <ProductId>1</ProductId>
    <ProductGroupId>0104</ProductGroupId>
  </ProductGroupMembership>
  <ProductGroupMembership>
    <ProductId>3</ProductId>
    <ProductGroupId>0103</ProductGroupId>
  </ProductGroupMembership>
  <ProductGroupMembership>
    <ProductId>3</ProductId>
    <ProductGroupId>01</ProductGroupId>
  </ProductGroupMembership>
  <ProductGroupMembership>
    <ProductId>4</ProductId>
    <ProductGroupId>0103</ProductGroupId>
  </ProductGroupMembership>
  <ProductGroupMembership>
    <ProductId>4</ProductId>
    <ProductGroupId>01</ProductGroupId>
  </ProductGroupMembership>
  <ProductGroupMembership>
    <ProductId>5</ProductId>
    <ProductGroupId>0103</ProductGroupId>
  </ProductGroupMembership>
  <ProductGroupMembership>
    <ProductId>5</ProductId>
    <ProductGroupId>01</ProductGroupId>
  </ProductGroupMembership>
  <ProductGroupMembership>
    <ProductId>6</ProductId>
    <ProductGroupId>0103</ProductGroupId>
  </ProductGroupMembership>
  <ProductGroupMembership>
    <ProductId>6</ProductId>
    <ProductGroupId>01</ProductGroupId>
  </ProductGroupMembership>
  <ProductGroupMembership>
    <ProductId>7</ProductId>
    <ProductGroupId>0102</ProductGroupId>
  </ProductGroupMembership>
  <ProductGroupMembership>
    <ProductId>7</ProductId>
    <ProductGroupId>01</ProductGroupId>
  </ProductGroupMembership>
  <ProductGroupMembership>
    <ProductId>8</ProductId>
    <ProductGroupId>0101</ProductGroupId>
  </ProductGroupMembership>
  <ProductGroupMembership>
    <ProductId>8</ProductId>
    <ProductGroupId>01</ProductGroupId>
  </ProductGroupMembership>
  <ProductGroupMembership>
    <ProductId>9</ProductId>
    <ProductGroupId>0101</ProductGroupId>
  </ProductGroupMembership>
  <ProductGroupMembership>
    <ProductId>9</ProductId>
    <ProductGroupId>01</ProductGroupId>
  </ProductGroupMembership>
  <ProductGroupMembership>
    <ProductId>10</ProductId>
    <ProductGroupId>0101</ProductGroupId>
  </ProductGroupMembership>
  <ProductGroupMembership>
    <ProductId>10</ProductId>
    <ProductGroupId>01</ProductGroupId>
  </ProductGroupMembership>
  <ProductGroupMembership>
    <ProductId>11</ProductId>
    <ProductGroupId>0101</ProductGroupId>
  </ProductGroupMembership>
  <ProductGroupMembership>
    <ProductId>11</ProductId>
    <ProductGroupId>01</ProductGroupId>
  </ProductGroupMembership>
  <ProductGroupMembership>
    <ProductId>12</ProductId>
    <ProductGroupId>0101</ProductGroupId>
  </ProductGroupMembership>
  <ProductGroupMembership>
    <ProductId>12</ProductId>
    <ProductGroupId>01</ProductGroupId>
  </ProductGroupMembership>
</ArrayOfProductGroupMembership>